raykit/__init__.py
raykit/package.py
raykit/version.py
raykit/utilis/__init__.py
raykit/utilis/parallel_utilis.py
raykit/utilis/torch_utilis.py
raykit/utilis/utilis.py
raykit-0.0.6.dist-info/LICENSE
raykit-0.0.6.dist-info/METADATA
raykit-0.0.6.dist-info/WHEEL
raykit-0.0.6.dist-info/top_level.txt
raykit-0.0.6.dist-info/RECORD
