Metadata-Version: 2.1
Name: raykit
Version: 0.0.6
Summary: A small utilis package
Home-page: https://github.com/AnyiRao/raykit
Author: Anyi Rao
Author-email: rayanyirao@gmail.com
License: MIT
Platform: UNKNOWN
Classifier: Programming Language :: Python :: 3
Classifier: License :: OSI Approved :: MIT License
Classifier: Operating System :: OS Independent
Requires-Dist: certifi (>=2019.6.16)
Requires-Dist: numpy (>=1.10.0)
Requires-Dist: tqdm (>=4.40.0)
